{
    "sourceFile": "components/sections/skills.tsx",
    "activeCommit": 0,
    "commits": [
        {
            "activePatchIndex": 0,
            "patches": [
                {
                    "date": 1774589234471,
                    "content": "Index: \n===================================================================\n--- \n+++ \n"
                }
            ],
            "date": 1774589234471,
            "name": "Commit-0",
            "content": "const skillCategories = [\r\n  {\r\n    level: \"Expert\",\r\n    skills: [\r\n      { name: \"HTML5\", category: \"Languages\" },\r\n      { name: \"CSS3 / SCSS\", category: \"Languages\" },\r\n      { name: \"JavaScript (ES6+)\", category: \"Languages\" },\r\n      { name: \"TypeScript\", category: \"Languages\" },\r\n      { name: \"React.js\", category: \"Frameworks\" },\r\n      { name: \"Tailwind CSS\", category: \"Styling\" },\r\n      { name: \"Responsive Design\", category: \"Styling\" },\r\n    ],\r\n  },\r\n  {\r\n    level: \"Experienced\",\r\n    skills: [\r\n      { name: \"Vue 3\", category: \"Frameworks\" },\r\n      { name: \"Vite\", category: \"Tools\" },\r\n      { name: \"Pinia\", category: \"State Management\" },\r\n      { name: \"Redux\", category: \"State Management\" },\r\n      { name: \"Vue Router\", category: \"Routing\" },\r\n      { name: \"React Router\", category: \"Routing\" },\r\n      { name: \"Git / GitHub\", category: \"Tools\" },\r\n      { name: \"Axios\", category: \"Tools\" },\r\n      { name: \"Figma to Code\", category: \"Tools\" },\r\n    ],\r\n  },\r\n  {\r\n    level: \"Knowledge\",\r\n    skills: [\r\n      { name: \"Node.js\", category: \"Backend\" },\r\n      { name: \"Express.js\", category: \"Backend\" },\r\n      { name: \"C# (.NET)\", category: \"Backend\" },\r\n      { name: \"SQL Server\", category: \"Database\" },\r\n      { name: \"Docker\", category: \"DevOps\" },\r\n    ],\r\n  },\r\n]\r\n\r\nexport function Skills() {\r\n  return (\r\n    <section id=\"experience\" className=\"py-24 px-6\">\r\n      <div className=\"mx-auto max-w-6xl\">\r\n        <div className=\"mb-12\">\r\n          <p className=\"text-primary font-mono text-sm mb-2\">02. Experience</p>\r\n          <h2 className=\"text-3xl md:text-4xl font-bold text-foreground\">\r\n            Technical Skills\r\n          </h2>\r\n          <p className=\"text-muted-foreground mt-4 max-w-2xl\">\r\n            My technical toolkit spans the modern frontend ecosystem with expertise in \r\n            building performant, accessible, and maintainable applications.\r\n          </p>\r\n        </div>\r\n\r\n        <div className=\"space-y-12\">\r\n          {skillCategories.map((category) => (\r\n            <div key={category.level} className=\"space-y-4\">\r\n              <div className=\"flex items-center gap-4\">\r\n                <h3 className=\"text-lg font-semibold text-foreground\">\r\n                  {category.level}\r\n                </h3>\r\n                <div className=\"h-px flex-1 bg-border\" />\r\n              </div>\r\n              <div className=\"flex flex-wrap gap-2\">\r\n                {category.skills.map((skill) => (\r\n                  <span\r\n                    key={skill.name}\r\n                    className=\"px-3 py-1.5 text-sm bg-secondary text-secondary-foreground rounded-md border border-border hover:border-primary/50 hover:bg-primary/10 transition-colors cursor-default\"\r\n                  >\r\n                    {skill.name}\r\n                  </span>\r\n                ))}\r\n              </div>\r\n            </div>\r\n          ))}\r\n        </div>\r\n\r\n        {/* Additional Info */}\r\n        <div className=\"mt-16 grid md:grid-cols-2 gap-8\">\r\n          <div className=\"p-6 rounded-lg border border-border bg-card\">\r\n            <h3 className=\"font-semibold text-foreground mb-2\">Languages</h3>\r\n            <ul className=\"space-y-2 text-muted-foreground\">\r\n              <li className=\"flex justify-between\">\r\n                <span>Vietnamese</span>\r\n                <span className=\"text-foreground\">Native</span>\r\n              </li>\r\n              <li className=\"flex justify-between\">\r\n                <span>English</span>\r\n                <span className=\"text-foreground\">Intermediate</span>\r\n              </li>\r\n            </ul>\r\n          </div>\r\n          <div className=\"p-6 rounded-lg border border-border bg-card\">\r\n            <h3 className=\"font-semibold text-foreground mb-2\">Education</h3>\r\n            <div className=\"text-muted-foreground\">\r\n              <p className=\"text-foreground font-medium\">\r\n                Ho Chi Minh City University of Technology (HUTECH)\r\n              </p>\r\n              <p>Software Engineering, 2022 - 2026</p>\r\n              <p className=\"text-primary\">GPA: 3.27 / 4.0</p>\r\n            </div>\r\n          </div>\r\n        </div>\r\n      </div>\r\n    </section>\r\n  )\r\n}\r\n"
        }
    ]
}